{
    "id": "facebook_template",
    "name": "Simple Facebook and Hibernate Example for CloudBees",
    "source": "git://github.com/CloudBees-community/facebook_template.git",
    "description" : "Build a database backed facebook app",
    "runtime": {
        "type": "tomcat"
    },
    "databases": [
        {
            "type": "mysql",
            "alias": "ExampleDS"
        }
    ],
    "build-with-jenkins": {
        "template": {
            "type": "maven",
            "options": {
            }
        }
    }
}